viviphi/__init__.py
viviphi/animator.py
viviphi/enums.py
viviphi/graph.py
viviphi/mermaid.py
viviphi/themes.py
viviphi-1.2.0.dist-info/licenses/LICENSE
viviphi-1.2.0.dist-info/METADATA
viviphi-1.2.0.dist-info/WHEEL
viviphi-1.2.0.dist-info/top_level.txt
viviphi-1.2.0.dist-info/RECORD
