Metadata-Version: 2.4
Name: viviphi
Version: 1.2.0
Summary: Turn static graphs into beautiful animations
Author-email: Davit Budaghyan <david@budaghyan.com>
Maintainer-email: Davit Budaghyan <david@budaghyan.com>
License-Expression: MIT
Project-URL: Homepage, https://github.com/viviphi/viviphi
Project-URL: Documentation, https://github.com/viviphi/viviphi#readme
Project-URL: Repository, https://github.com/viviphi/viviphi.git
Project-URL: Bug Tracker, https://github.com/viviphi/viviphi/issues
Keywords: animation,svg,mermaid,graphs,diagrams,visualization
Classifier: Development Status :: 5 - Production/Stable
Classifier: Intended Audience :: Developers
Classifier: Intended Audience :: Education
Classifier: Operating System :: OS Independent
Classifier: Programming Language :: Python :: 3
Classifier: Programming Language :: Python :: 3.13
Classifier: Topic :: Multimedia :: Graphics
Classifier: Topic :: Scientific/Engineering :: Visualization
Classifier: Topic :: Software Development :: Libraries :: Python Modules
Classifier: Topic :: Text Processing :: Markup :: HTML
Requires-Python: >=3.13
License-File: LICENSE
Requires-Dist: httpx>=0.28.1
Requires-Dist: jinja2>=3.1.6
Requires-Dist: litellm>=1.80.7
Requires-Dist: loguru>=0.7.3
Requires-Dist: lxml>=6.0.2
Requires-Dist: matplotlib>=3.10.7
Requires-Dist: networkx>=3.6
Requires-Dist: playwright>=1.56.0
Requires-Dist: pydantic>=2.12.5
Requires-Dist: svgpathtools>=1.7.1
Dynamic: license-file
